FileIOPy/__init__.py
FileIOPy-1.1.dist-info/LICENCE.txt
FileIOPy-1.1.dist-info/METADATA
FileIOPy-1.1.dist-info/WHEEL
FileIOPy-1.1.dist-info/top_level.txt
FileIOPy-1.1.dist-info/RECORD
