Metadata-Version: 2.1
Name: FileIOPy
Version: 1.1
Summary: A simple and easy File IO package for python
Home-page: UNKNOWN
Author: Aditya Kshirsagar
Author-email: adityamksagar@gmail.com
License: UNKNOWN
Platform: UNKNOWN
Classifier: Programming Language :: Python :: 3
Classifier: License :: OSI Approved :: MIT License
Classifier: Operating System :: OS Independent
